{
  "cards": {
    "0": {
      "name": "愚者",
      "name_en": "The Fool",
      "image_url": "https://sacred-texts.com/tarot/pkt/img/ar00.jpg",
      "upright": {
        "keywords": ["新開始", "冒險", "自由"],
        "meanings": {
          "general": "進入全新階段，擁有無限可能。\n放下恐懼，憑直覺踏出冒險第一步。",
          "love": "開啟全新關係，不預設任何結果。\n注入純真、無拘無束的新能量。",
          "career": "適合創業或轉換全新跑道。\n熱情與勇氣是你最強大的資產。"
        },
        "advice": "保持開放心態，不讓過去限制想像力。\n相信宇宙，在你跳下時自會有人接住你。"
      },
      "reversed": {
        "keywords": ["魯莽", "風險", "遲疑"],
        "meanings": {
          "general": "行動過於衝動，缺乏風險評估。\n或因害怕未知而原地踏步，流失機會。",
          "love": "面臨不負責任的承諾或短暫迷戀。\n過於追求自由而忽視對方的安全感。",
          "career": "面臨不穩定風險，需審視計劃漏洞。\n避免盲目衝刺導致無謂損失。"
        },
        "advice": "冒險前先看清腳下的懸崖。\n現在需要審慎規劃，而非盲目熱血。"
      }
    },
    "1": {
      "name": "魔術師",
      "name_en": "The Magician",
      "image_url": "https://sacred-texts.com/tarot/pkt/img/ar01.jpg",
      "upright": {
        "keywords": ["創造力", "技能", "行動力"],
        "meanings": {
          "general": "萬事具備，擁有實現目標的工具。\n將想法轉化為現實的黃金時機。",
          "love": "充滿吸引力與良好溝通的關係。\n展現自信魅力，主導情感正向走向。",
          "career": "具備多工處理能力，表現優異。\n新計劃極易成功，充分展現專業威信。"
        },
        "advice": "集中意念並付諸行動。\n你具備改變現狀的力量，別浪費天賦。"
      },
      "reversed": {
        "keywords": ["操縱", "浪費天賦", "溝通不暢"],
        "meanings": {
          "general": "想法難以落實，能量被分散。\n注意周遭是否存在欺瞞或不誠實。",
          "love": "存在甜言蜜語但缺乏真誠的傾向。\n雙方玩心理遊戲，缺乏真正信任。",
          "career": "專業技能未發揮，因自信不足錯失良機。\n小心資訊不對稱，避免被他人誤導。"
        },
        "advice": "重新審視你的真實動機。\n確認是否在逃避責任或掩蓋準備不足。"
      }
    },
    "2": {
      "name": "女祭司",
      "name_en": "The High Priestess",
      "image_url": "https://sacred-texts.com/tarot/pkt/img/ar02.jpg",
      "upright": {
        "keywords": ["直覺", "內在智慧", "神秘"],
        "meanings": {
          "general": "向內探索的時刻，外在看似平靜。\n直覺正給予強烈指引，適合靜心觀察。",
          "love": "代表精神連結，關係處於觀望階段。\n重點在於心靈共鳴，而非感官進展。",
          "career": "不宜急於表現，適合深度研究規劃。\n依賴洞察力處理問題，保持低調有利。"
        },
        "advice": "傾聽內心微小的聲音。\n答案藏在寂靜中，信任你的第一直覺。"
      },
      "reversed": {
        "keywords": ["忽視直覺", "秘密揭露", "浮躁"],
        "meanings": {
          "general": "過於依賴邏輯而忽視潛在警訊。\n紛擾讓你失去平靜，變得容易焦慮。",
          "love": "感情中隱藏著不安或未說出口的秘密。\n過於壓抑情感，導致關係疏離冷漠。",
          "career": "缺乏對局勢的洞察，急躁導致隱患。\n注意資訊真實性，別被表面承諾迷惑。"
        },
        "advice": "停止尋找外在認同。\n回到內心，釐清情緒與真實指引。"
      }
    },
    "3": {
      "name": "皇后",
      "name_en": "The Empress",
      "image_url": "https://sacred-texts.com/tarot/pkt/img/ar03.jpg",
      "upright": {
        "keywords": ["豐收", "母性", "自然"],
        "meanings": {
          "general": "進入豐盛豐饒的時期，富有生命力。\n適合滋養你的計畫，讓其自然成長。",
          "love": "充滿溫暖、感性與照顧的關係。\n可能代表家庭關係的和諧或新生命的到來。",
          "career": "創意如泉湧，計畫正走向開花結果。\n適合從事美感、藝術或照護相關工作。"
        },
        "advice": "連結你的感官，享受當下的美好。\n溫柔地對待自己與他人。"
      },
      "reversed": {
        "keywords": ["創造力阻滯", "依賴", "虛榮"],
        "meanings": {
          "general": "感到匱乏或創造力乾涸。\n可能過於保護或溺愛，導致成長停滯。",
          "love": "在感情中過於黏人，失去自我空間。\n或因缺乏安全感而過度索求關注。",
          "career": "計畫進展緩慢，缺乏實質的推動力。\n注意資源浪費，別只追求表面排場。"
        },
        "advice": "找回內心的自足與平靜。\n過度給予之前，先學會滋養自己的靈魂。"
      }
    },
    "4": {
      "name": "皇帝",
      "name_en": "The Emperor",
      "image_url": "https://sacred-texts.com/tarot/pkt/img/ar04.jpg",
      "upright": {
        "keywords": ["權威", "結構", "穩定"],
        "meanings": {
          "general": "建立秩序與規則，代表穩定環境。\n領導力強大，能將計劃導向成功。",
          "love": "關係穩定帶有保護慾，提供安全感。\n伴侶扮演帶領者角色，重視承諾。",
          "career": "事業運強，適合執行嚴謹長遠計劃。\n有晉升機會，建立可長可久的體制。"
        },
        "advice": "運用邏輯、策略與紀律。\n現在需要果斷執行，而非情緒化猶豫。"
      },
      "reversed": {
        "keywords": ["專制", "僵化", "失控"],
        "meanings": {
          "general": "面臨過度控制環境，或因不自律失控。\n權威受到挑戰，感到力不從心。",
          "love": "出現權力不對等、固執的溝通障礙。\n掌控慾讓對方窒息，需要學習放手。",
          "career": "遭遇官僚主義打壓，計劃過於死板。\n自律能力下降，工作進度不如預期。"
        },
        "advice": "學習彈性，強大來自包容而非強迫。\n反思固執是否成為進步最大的障礙。"
      }
    },
    "5": {
      "name": "教皇",
      "name_en": "The Hierophant",
      "image_url": "https://sacred-texts.com/tarot/pkt/img/ar05.jpg",
      "upright": {
        "keywords": ["傳統", "教導", "信守規則"],
        "meanings": {
          "general": "遵循傳統價值觀與體制，獲得指引。\n適合尋求專業人士或導師的建議。",
          "love": "重視精神契合與傳統形式的關係。\n可能涉及婚姻或建立更嚴肅的承諾。",
          "career": "在大型組織中發展穩定，遵循制度。\n適合學習新技能或進行在職進修。"
        },
        "advice": "尊重規矩，在體制內尋求解決之道。\n傾聽過來人的經驗，不要急於反叛。"
      },
      "reversed": {
        "keywords": ["反叛", "教條主義", "非正規"],
        "meanings": {
          "general": "挑戰權威，質疑陳舊的規則。\n不願隨波逐流，想走出一條獨特的道路。",
          "love": "不滿傳統關係束縛，尋求非典型的互動。\n或因雙方價值觀與社會標準衝突而焦慮。",
          "career": "不適應現有的工作模式，想打破限制。\n注意不要為了反對而反對，需有實質計畫。"
        },
        "advice": "思考傳統中哪些值得保留，哪些該捨棄。\n打破規則前，先確認自己已理解規則。"
      }
    },
    "6": {
      "name": "戀人",
      "name_en": "The Lovers",
      "image_url": "https://sacred-texts.com/tarot/pkt/img/ar06.jpg",
      "upright": {
        "keywords": ["選擇", "結合", "價值觀"],
        "meanings": {
          "general": "面臨重要的十字路口，需做決定。\n不僅關乎愛情，也關乎內在價值的對齊。",
          "love": "靈魂伴侶般的連結，充滿和諧與火花。\n這是一段基於互信與共同理想的關係。",
          "career": "出現合作契機，需權衡各方利弊。\n選擇一份符合你內心真正渴望的工作。"
        },
        "advice": "聽從心底最真實的渴望。\n做決定時，優先考慮你的長遠價值觀。"
      },
      "reversed": {
        "keywords": ["失衡", "逃避選擇", "不合"],
        "meanings": {
          "general": "感到內外失調，難以做出明確決定。\n可能正逃避某個迫在眉睫的責任。",
          "love": "溝通斷裂，雙方步調不再一致。\n注意誘惑與第三方的干擾影響感情。"
        },
        "advice": "重新釐清你的目標與現狀。\n修補關係前，先修補你自己內心的混亂。"
      }
    },
    "7": {
      "name": "戰車",
      "name_en": "The Chariot",
      "image_url": "https://sacred-texts.com/tarot/pkt/img/ar07.jpg",
      "upright": {
        "keywords": ["勝利", "自律", "意志"],
        "meanings": {
          "general": "憑藉強大的意志力克服重重阻礙。\n這是一張代表成功、進展與動力的牌。",
          "love": "主動追求並掌握情感的主導權。\n雙方共同朝著目標前進，克服外界阻撓。",
          "career": "事業突飛猛進，競爭力極強。\n透過高度自律與專注，達成預定目標。"
        },
        "advice": "保持專注，將不同的能量引向同一個方向。\n現在是全速前進的時刻，不要猶豫。"
      },
      "reversed": {
        "keywords": ["失控", "侵略性", "方向不明"],
        "meanings": {
          "general": "感到生活失去控制，情緒或外在混亂。\n力量用錯了地方，導致徒勞無功。",
          "love": "關係中出現過激的爭執或控制欲。\n或因缺乏長遠共識，讓雙方感到疲憊。",
          "career": "急於求成而忽略風險，導致計畫挫敗。\n注意職場的人際摩擦，避免過於強勢。"
        },
        "advice": "先停下來，重新拿回對自己的主導權。\n檢查你的方向盤是否歪了，調整後再出發。"
      }
    },
    "8": {
      "name": "力量",
      "name_en": "Strength",
      "image_url": "https://sacred-texts.com/tarot/pkt/img/ar08.jpg",
      "upright": {
        "keywords": ["勇氣", "耐心", "內在力量"],
        "meanings": {
          "general": "以柔克剛，運用內在勇氣面對挑戰。\n不是靠蠻力，而是靠智慧與耐心收服困境。",
          "love": "一段成熟且充滿耐心的關係。\n你能以包容的心感化對方的脾氣與弱點。",
          "career": "具備強大的抗壓性，能處理棘手事務。\n運用你的親和力與說服力，而非權威來共事。"
        },
        "advice": "溫柔就是最強大的力量。\n相信自己的韌性，不要被暫時的恐懼擊垮。"
      },
      "reversed": {
        "keywords": ["軟弱", "缺乏勇氣", "本能失控"],
        "meanings": {
          "general": "感到內心脆弱，容易被負面情緒淹沒。\n或是對自己的本能衝動感到控制不住。",
          "love": "因缺乏信心而對感情感到退縮。\n注意脾氣暴躁導致的冷戰或傷人的言語。",
          "career": "在困難面前輕易放棄，缺乏持之以恆的毅力。\n容易被壓力壓垮，需要找回內在的中心。"
        },
        "advice": "原諒自己的脆弱，慢慢重拾自信。\n你需要與內心的怪獸握手言和，而非逃避它。"
      }
    },
    "9": {
      "name": "隱士",
      "name_en": "The Hermit",
      "image_url": "https://sacred-texts.com/tarot/pkt/img/ar09.jpg",
      "upright": {
        "keywords": ["孤獨", "內省", "引導"],
        "meanings": {
          "general": "暫時退回到自己的世界，尋求真理。\n這是一段深刻的內省期，而非孤立無援。",
          "love": "享受獨處，或是需要空間思索感情方向。\n感情趨向平淡深層，而非外在的熱烈。",
          "career": "適合專注於獨立研究或技術鑽研。\n現在不是擴展期，而是精進專業的高峰期。"
        },
        "advice": "靜下來，聽聽靈魂在說什麼。\n真理在你的內心，不需要去外面尋找。"
      },
      "reversed": {
        "keywords": ["孤立", "偏執", "拒絕指引"],
        "meanings": {
          "general": "感到被世界遺忘，陷入無效的孤寂。\n可能過於固執，不願接受他人的客觀建議。",
          "love": "關係中感到孤單，溝通徹底中斷。\n或是因為害怕受傷而過度封閉自己。",
          "career": "因離群索居而錯失重要的團隊資訊。\n鑽牛角尖，把簡單的問題複雜化了。"
        },
        "advice": "適度踏出自己的世界，與人交流。\n別讓內心的燈火熄滅，試著接納外界的光芒。"
      }
    },
    "10": {
      "name": "命運之輪",
      "name_en": "Wheel of Fortune",
      "image_url": "https://sacred-texts.com/tarot/pkt/img/ar10.jpg",
      "upright": {
        "keywords": ["改變", "循環", "契機"],
        "meanings": {
          "general": "幸運之神降臨，生活將迎來轉折。\n接受變化，這是一個不可逆的良性發展。",
          "love": "命中註定的相遇，或是關係進入新階段。\n這是一場緣分的奇妙安排，請順勢而為。",
          "career": "突如其來的好機會，適合大膽行動。\n職涯出現轉機，過去的努力開始得到回報。"
        },
        "advice": "順應時勢，不要抵抗改變。\n掌握命運推動的頻率，積極把握眼前的時機。"
      },
      "reversed": {
        "keywords": ["厄運", "抵抗變化", "重蹈覆轍"],
        "meanings": {
          "general": "感到事與願違，似乎一切都在跟你作對。\n現在不適合採取重大行動，需等待時機。",
          "love": "感情進入瓶頸，感到難以維持現狀。\n舊有的問題反覆出現，卻找不到出口。",
          "career": "進展停滯或出現意外的阻礙。\n不要在此時硬碰硬，學習在低潮中儲存能量。"
        },
        "advice": "接受低谷，這也是生命循環的一部分。\n檢視哪些模式一直重複，現在是打破它的機會。"
      }
    },
    "11": {
      "name": "正義",
      "name_en": "Justice",
      "image_url": "https://sacred-texts.com/tarot/pkt/img/ar11.jpg",
      "upright": {
        "keywords": ["公平", "真相", "法律"],
        "meanings": {
          "general": "因果報應的展現，你將得到應得的結果。\n強調誠實、公正與理性的判斷。",
          "love": "一段平等、誠實且互相尊重的關係。\n對於不合適的關係，則代表做出理性的了斷。",
          "career": "職場上的法律事務或合約進展順利。\n你的表現將得到公平的評估，多勞多得。"
        },
        "advice": "保持客觀，不做情緒化的判斷。\n對自己的行為負起責任，真相終會揭曉。"
      },
      "reversed": {
        "keywords": ["不公", "偏見", "逃避責任"],
        "meanings": {
          "general": "感到遭遇不公平對待，或有黑箱作業。\n拒絕承認事實，試圖逃避應有的責任。",
          "love": "關係中出現謊言、欺瞞或不對等。\n雙方互推責任，無法冷靜處理問題。",
          "career": "工作成果被剽竊，或面臨合約糾紛。\n注意偏見可能影響判斷，小心法律地雷。"
        },
        "advice": "檢討自己是否也有不誠實的地方。\n只有面對真相，混亂才能真正平息。"
      }
    },
    "12": {
      "name": "倒吊人",
      "name_en": "The Hanged Man",
      "image_url": "https://sacred-texts.com/tarot/pkt/img/ar12.jpg",
      "upright": {
        "keywords": ["換位思考", "犧牲", "暫停"],
        "meanings": {
          "general": "換一個角度看世界，會發現全新的出口。\n這是一個寧靜的等待期，強求無效。",
          "love": "在感情中默默付出，或是選擇退一步思考。\n不急著要答案，而是觀察這段關係的本質。",
          "career": "工作進展緩慢，像是卡住了，但這是磨練心志。\n適合學習與觀摩，不要急著在此時強出頭。"
        },
        "advice": "停下來，別急著掙扎。\n目前的困境是為了讓你看到原本忽略的觀點。"
      },
      "reversed": {
        "keywords": ["無謂犧牲", "原地踏步", "固執"],
        "meanings": {
          "general": "感到在浪費時間，犧牲卻得不到回報。\n不願改變觀點，只是在無謂地受苦。",
          "love": "感情中單方面的自我感動，卻無法打動對方。\n陷入死循環卻不願放手，感到深深的無力感。",
          "career": "做著不感興趣的工作，感到生活枯燥乏味。\n固守舊思維，導致與外界發展脫節。"
        },
        "advice": "停止無謂的等待，該採取行動打破僵局了。\n檢視你的犧牲是否有價值，還是只是在逃避改變。"
      }
    },
    "13": {
      "name": "死神",
      "name_en": "Death",
      "image_url": "https://sacred-texts.com/tarot/pkt/img/ar13.jpg",
      "upright": {
        "keywords": ["結束", "轉變", "新生"],
        "meanings": {
          "general": "一個舊階段的徹底終結，為新生活騰出空間。\n不必恐懼，這是一個自然的汰舊換新過程。",
          "love": "關係的重大轉變，可能代表分手或重生。\n捨棄不健康的相處模式，感情才能進化。",
          "career": "職涯上的大變動，如離職、轉行或裁撤。\n雖然短期有陣痛，但這是邁向更好的開始。"
        },
        "advice": "揮別過去，不要再眷戀已經死去的東西。\n只有當舊的門關上，新的窗戶才會開啟。"
      },
      "reversed": {
        "keywords": ["抗拒改變", "停滯", "不願放手"],
        "meanings": {
          "general": "緊抓著過去不放，讓痛苦持續延長。\n恐懼改變帶來的未知，即使現狀已經腐壞。",
          "love": "藕斷絲連，陷入一段早就該結束的關係。\n恐懼單身或孤獨，寧願忍受低質量的陪伴。",
          "career": "待在沒有前途的環境裡，害怕轉換跑道。\n這種拖延只會讓未來的機會越來越渺茫。"
        },
        "advice": "接受死亡是生命的一部分。\n越是抵抗，痛苦就越深；試著平靜地說再見。"
      }
    },
    "14": {
      "name": "節制",
      "name_en": "Temperance",
      "image_url": "https://sacred-texts.com/tarot/pkt/img/ar14.jpg",
      "upright": {
        "keywords": ["平衡", "和諧", "融合"],
        "meanings": {
          "general": "找尋中庸之道，情緒與理智達到和諧。\n這是一段療癒期，事物正在慢慢趨於穩定。",
          "love": "穩定且充滿默契的關係，雙方能互補長短。\n透過良好的溝通，化解矛盾，達成深度共識。",
          "career": "工作安排井然有序，能夠兼顧各方利益。\n適合調解與整合資源，進展順利且長久。"
        },
        "advice": "保持耐心，慢慢地將生活拼湊整齊。\n尋求平衡點，不要讓自己陷入任何極端。"
      },
      "reversed": {
        "keywords": ["失衡", "過度", "缺乏目的"],
        "meanings": {
          "general": "感到生活失去重心，身心靈出現衝突。\n缺乏耐心，試圖快速達成目標卻弄巧成拙。",
          "love": "情感需求過度，或與伴侶步調嚴重不一致。\n溝通出現雞同鴨講，缺乏真正的共鳴。",
          "career": "資源分配不均，或是工作量過負荷。\n缺乏清晰的規劃，導致事情變得雜亂無章。"
        },
        "advice": "重新校正你的頻率。\n找出讓你失衡的原因，並優先處理最核心的問題。"
      }
    },
    "15": {
      "name": "惡魔",
      "name_en": "The Devil",
      "image_url": "https://sacred-texts.com/tarot/pkt/img/ar15.jpg",
      "upright": {
        "keywords": ["束縛", "慾望", "物質享受"],
        "meanings": {
          "general": "被慾望或不良習慣所束縛，感到身不由己。\n這是一張提醒你要覺察成癮與執著的牌。",
          "love": "強烈的感官吸引，甚至是帶有控制慾的愛。\n要注意這段關係是否讓你失去了獨立性。",
          "career": "過於追求金錢與權力，陷入職場的權力遊戲。\n感到被困在目前的職位上，卻因為福利而不敢離開。"
        },
        "advice": "解開鎖鏈的鑰匙就在你手中。\n意識到你的束縛是自找的，你隨時有權利離開。"
      },
      "reversed": {
        "keywords": ["覺醒", "解脫", "重獲自由"],
        "meanings": {
          "general": "意識到問題所在，開始嘗試擺脫舊有的束縛。\n這是一個自我救贖的過程，開始重掌生活主權。",
          "love": "看穿了有害關係的本質，開始設定底線。\n逐漸從一段不健康的感情中康復過來。",
          "career": "對名利不再盲目追求，尋找真正有意義的方向。\n突破職涯瓶頸，找到新的動力來源。"
        },
        "advice": "現在是拿回掌控權的最好時機。\n勇敢地面對陰暗面，你將獲得重生。"
      }
    },
    "16": {
      "name": "高塔",
      "name_en": "The Tower",
      "image_url": "https://sacred-texts.com/tarot/pkt/img/ar16.jpg",
      "upright": {
        "keywords": ["劇變", "崩塌", "真相大白"],
        "meanings": {
          "general": "突如其來的劇變，原本穩固的結構瞬間瓦解。\n這雖然震驚，卻是為了摧毀虛假與不切實際。",
          "love": "關係中爆發嚴重的衝突，或秘密被揭露。\n這是一個痛苦但必要的清掃過程，讓真相浮現。",
          "career": "職場上的突發危機，可能是公司倒閉或裁員。\n原本的計劃被打亂，迫使你必須重新開始。"
        },
        "advice": "不要試圖挽救即將崩塌的建築。\n讓不穩定的東西倒下，你才有機會在廢墟中重建。"
      },
      "reversed": {
        "keywords": ["延遲崩潰", "逃避災難", "不徹底的改變"],
        "meanings": {
          "general": "感到災難在醞釀中，但尚未徹底爆發。\n你正試圖延緩變革，但這可能只是治標不治本。",
          "love": "關係處於危險邊緣，雙方都在勉強維持表面的平靜。\n小心長期壓抑的情緒，爆發時會更加猛烈。",
          "career": "工作環境惡劣，但你選擇繼續忍受。\n缺乏重頭再來的勇氣，導致身心俱疲。"
        },
        "advice": "與其害怕崩潰，不如主動改革。\n拖延只會讓未來的代價更高，勇敢面對必須的改變。"
      }
    },
    "17": {
      "name": "星星",
      "name_en": "The Star",
      "image_url": "https://sacred-texts.com/tarot/pkt/img/ar17.jpg",
      "upright": {
        "keywords": ["希望", "療癒", "平靜"],
        "meanings": {
          "general": "在黑暗後迎來曙光，靈魂得到深刻的撫慰。\n這是一張充滿祝福、靈感與對未來的信心的牌。",
          "love": "關係進入療癒期，充滿溫柔與理解。\n對於單身者，代表有新的希望與正向的緣分出現。",
          "career": "才華得到展現，前景一片大好。\n你在工作中的理想正在慢慢實現，深受他人啟發。"
        },
        "advice": "保持希望，宇宙正在引導你。\n現在是放鬆與修復的最佳時機，信任生命。 "
      },
      "reversed": {
        "keywords": ["失望", "悲觀", "靈感匱乏"],
        "meanings": {
          "general": "感到迷失方向，對未來缺乏信心與熱情。\n或是因為過高的期待落空，而陷入深深的沮喪。",
          "love": "感情中感到乏味或絕望，看不見未來。\n缺乏精神連結，只是在維持日常的運作。",
          "career": "計畫受阻，感到才華被埋沒。\n缺乏創意與推動力，對工作感到前途渺茫。"
        },
        "advice": "重新點燃內心的亮光。\n即使在黑夜中，星星依然存在，只是你暫時低下了頭。"
      }
    },
    "18": {
      "name": "月亮",
      "name_en": "The Moon",
      "image_url": "https://sacred-texts.com/tarot/pkt/img/ar18.jpg",
      "upright": {
        "keywords": ["不安", "幻覺", "隱藏的恐懼"],
        "meanings": {
          "general": "真相不明，環境充滿了混亂與不確定性。\n容易受情緒影響，產生不切實際的幻想或恐懼。",
          "love": "感情中充滿猜忌與不安，看不清對方的真心。\n可能存在隱藏的競爭者，或雙方都在逃避問題。",
          "career": "職場環境複雜，隱藏著不為人知的內幕。\n現在不適合簽約或做決定，因為資訊不夠透明。"
        },
        "advice": "相信你的直覺，而非表面所見。\n在迷霧中保持冷靜，等待月光照亮腳下的路。"
      },
      "reversed": {
        "keywords": ["真相大白", "恐懼消失", "緩解"],
        "meanings": {
          "general": "迷霧逐漸散去，原本困擾你的不安正在平息。\n你開始看清局勢的真相，從幻想中覺醒。",
          "love": "猜疑得到解釋，雙方的誤會逐漸消除。\n或者是你終於決定面對感情中的那些陰暗面。",
          "career": "職場中的流言蜚語停止，局面趨於清晰。\n原本隱藏的問題浮出水面，可以被針對性地解決。"
        },
        "advice": "勇敢面對那些讓你害怕的東西。\n當光線照進黑暗，原本的怪物其實只是影子。"
      }
    },
    "19": {
      "name": "太陽",
      "name_en": "The Sun",
      "image_url": "https://sacred-texts.com/tarot/pkt/img/ar19.jpg",
      "upright": {
        "keywords": ["喜悅", "成功", "活力"],
        "meanings": {
          "general": "光明、溫暖與極度的成功降臨在你的生活中。\n這是一張代表最極致快樂與正能量的牌。",
          "love": "充滿熱情與陽光的感情生活，受到大眾祝福。\n雙方相處坦承且充滿歡笑，是非常美滿的關係。",
          "career": "事業達到巔峰，成果豐碩且備受肯定。\n如果你有任何新計劃，現在正是最合適的執行時機。"
        },
        "advice": "大方展現你的才華，享受當下的快樂。\n保持像孩子一樣的純真與信心，好運將與你同行。"
      },
      "reversed": {
        "keywords": ["過度樂觀", "暫時阻滯", "延遲"],
        "meanings": {
          "general": "依然有成功，但可能不如預期那樣亮眼。\n或是因為過度自信而忽略了細小的潛在問題。",
          "love": "感情大致穩定，但缺乏了一些激情或活力。\n或者是雙方都在勉強展現快樂，內心卻有些疲憊。",
          "career": "進展受到一點延遲，但大方向依然是正確的。\n不要太過張揚，腳踏實地地完成最後一段路。"
        },
        "advice": "調整心態，保持感恩的心。\n即使陽光被雲遮住了，它依然在雲層背後發光。"
      }
    },
    "20": {
      "name": "審判",
      "name_en": "Judgement",
      "image_url": "https://sacred-texts.com/tarot/pkt/img/ar20.jpg",
      "upright": {
        "keywords": ["召喚", "重生", "因果"],
        "meanings": {
          "general": "聽到命運的號角，生活面臨重大的重生與覺醒。\n這是一個總結過去並邁向未來的關鍵時刻。",
          "love": "感情關係面臨重大的決斷或復合的可能。\n雙方都對過去的行為有了深刻的體悟，重新出發。",
          "career": "事業上的重大轉機，有機會重新證明自己。\n你的努力將得到公正的裁決，迎來晉升或新契機。"
        },
        "advice": "原諒過去的自己，勇敢接受新的召喚。\n這是一個脫胎換骨的機會，請做好準備。"
      },
      "reversed": {
        "keywords": ["猶豫", "拒絕召喚", "自責"],
        "meanings": {
          "general": "害怕面對結果，對過去的事耿耿於懷。\n拒絕改變現狀，即使那是對你更好的方向。",
          "love": "沈溺於過去的傷害，無法開啟新的生活。\n關係停留在互相指責中，無法達成共識或解脫。",
          "career": "職場上缺乏果斷，錯失了重要的轉型機會。\n過於自責過去的失敗，讓你失去了前進的動力。"
        },
        "advice": "停止批判自己，放下沉重的包袱。\n號角已經響起，如果你不前進，就只能留在原地。"
      }
    },
    "21": {
      "name": "世界",
      "name_en": "The World",
      "image_url": "https://sacred-texts.com/tarot/pkt/img/ar21.jpg",
      "upright": {
        "keywords": ["圓滿", "達成", "旅行"],
        "meanings": {
          "general": "一段旅程的完美結束，達成目標並獲得成就感。\n生活各個層面達到了和諧與圓滿的巔峰狀態。",
          "love": "感情關係開花結果，邁向婚姻或更穩定的未來。\n這是一段靈魂與物質雙重滿足的幸福關係。",
          "career": "計畫大獲成功，在專業領域獲得極高聲譽。\n可能會有海外發展或跨領域成功的機會。"
        },
        "advice": "慶祝你的成就，享受這一刻的豐盛。\n記住這一刻的圓滿，並為下一段旅程做好準備。"
      },
      "reversed": {
        "keywords": ["未完成", "遺憾", "缺乏成就感"],
        "meanings": {
          "general": "事情接近尾聲但最後一哩路沒走完。\n或是雖然達成了目標，卻感到空虛與不滿足。",
          "love": "關係遲遲無法進入下一個階段，感到受阻。\n雖然雙方在一起，但心靈深處總覺得缺了一角。",
          "career": "工作進展停在最後一關，缺乏臨門一腳。\n即使表面成功，內心卻對目前的成就感到懷疑。"
        },
        "advice": "檢查哪裡還有遺漏的細節沒處理好。\n別急著結束，把剩下的拼圖拼完才能真正圓滿。"
      }
    }
  },
  "embed": {
    "footer": {
      "text": ""
    }
  },
  "colors": {
    "upright": "#9b59b6",
    "reversed": "#95a5a6"
  }
}
